{"cookies": [{"name": "fp", "value": "a0068f427fe53b6eec301d439821c703f", "domain": ".note.com", "path": "/", "expires": -1, "httpOnly": false, "secure": false, "sameSite": "Lax"}, {"name": "_vid_v2", "value": "64b2c6b9492c2c3402b44fec26fa7bb8", "domain": ".note.com", "path": "/", "expires": -1, "httpOnly": false, "secure": false, "sameSite": "Lax"}, {"name": "_gid", "value": "GA1.2.395740408.1775916486", "domain": ".note.com", "path": "/", "expires": 1776002892, "httpOnly": false, "secure": false, "sameSite": "Lax"}, {"name": "_note_session_v5", "value": "62796ae4b36593d276eb574b50f21bc1", "domain": ".note.com", "path": "/", "expires": 1783778909.845419, "httpOnly": true, "secure": true, "sameSite": "Lax"}, {"name": "_ga", "value": "GA1.1.1448265097.1775916486", "domain": ".note.com", "path": "/", "expires": 1810476492.787055, "httpOnly": false, "secure": false, "sameSite": "Lax"}, {"name": "_ga_J9CPC3WE56", "value": "GS2.1.s1775916486$o1$g1$t1775916497$j49$l0$h0", "domain": ".note.com", "path": "/", "expires": 1810476497.245355, "httpOnly": false, "secure": false, "sameSite": "Lax"}, {"name": "fp", "value": "36331e0e95e5bf39f56a1eecc1afedfec", "domain": ".editor.note.com", "path": "/", "expires": -1, "httpOnly": false, "secure": false, "sameSite": "Lax"}, {"name": "_vid_v1", "value": "0b624e22cc4e8f91fadd456fc1c67ec2", "domain": "note.com", "path": "/", "expires": -1, "httpOnly": false, "secure": false, "sameSite": "Lax"}, {"name": "_vid_v1", "value": "0b624e22cc4e8f91fadd456fc1c67ec2", "domain": ".editor.note.com", "path": "/", "expires": 1775918288, "httpOnly": false, "secure": false, "sameSite": "Lax"}], "origins": [{"origin": "https://editor.note.com", "localStorage": [{"name": "assistants-errors", "value": "{\"count\":0,\"lastErrorAt\":0}"}]}, {"origin": "https://note.com", "localStorage": [{"name": "confirmAnniversaryBadge", "value": "2026/04/11"}, {"name": "note-client-code", "value": "91475c41aa308d0927672beb69ba0818aae9014140e0a9f59e969a8466e81810"}, {"name": "showingCategory", "value": "1,2,3,4,5,6,7"}]}]}